{"scriptId":"88","url":"file:///home/juanperez/dev/plain-db/src/rules.ts","functions":[{"functionName":"","ranges":[{"startOffset":0,"endOffset":1802,"count":1}],"isBlockCoverage":true},{"functionName":"_read","ranges":[{"startOffset":37,"endOffset":45,"count":176}],"isBlockCoverage":true},{"functionName":"_write","ranges":[{"startOffset":64,"endOffset":72,"count":132}],"isBlockCoverage":true},{"functionName":"_read","ranges":[{"startOffset":112,"endOffset":121,"count":0}],"isBlockCoverage":false},{"functionName":"_write","ranges":[{"startOffset":140,"endOffset":149,"count":0}],"isBlockCoverage":false},{"functionName":"_read","ranges":[{"startOffset":192,"endOffset":200,"count":1}],"isBlockCoverage":true},{"functionName":"_write","ranges":[{"startOffset":236,"endOffset":267,"count":3}],"isBlockCoverage":true},{"functionName":"_read","ranges":[{"startOffset":316,"endOffset":324,"count":0}],"isBlockCoverage":false},{"functionName":"_write","ranges":[{"startOffset":360,"endOffset":426,"count":0}],"isBlockCoverage":false}]}